sparrow_cloud/__init__.py
sparrow_cloud/access_control/__init__.py
sparrow_cloud/access_control/access_verify.py
sparrow_cloud/access_control/base_access_control.py
sparrow_cloud/access_control/decorators.py
sparrow_cloud/app_message/__init__.py
sparrow_cloud/app_message/sender.py
sparrow_cloud/apps/__init__.py
sparrow_cloud/apps/access_control/__init__.py
sparrow_cloud/apps/access_control/admin.py
sparrow_cloud/apps/access_control/apps.py
sparrow_cloud/apps/access_control/example_access_control.py
sparrow_cloud/apps/access_control/models.py
sparrow_cloud/apps/access_control/tests.py
sparrow_cloud/apps/access_control/views.py
sparrow_cloud/apps/access_control/management/__init__.py
sparrow_cloud/apps/access_control/management/commands/__init__.py
sparrow_cloud/apps/access_control/management/commands/register_access_control.py
sparrow_cloud/apps/access_control/migrations/__init__.py
sparrow_cloud/apps/message_service/__init__.py
sparrow_cloud/apps/message_service/admin.py
sparrow_cloud/apps/message_service/apps.py
sparrow_cloud/apps/message_service/models.py
sparrow_cloud/apps/message_service/tests.py
sparrow_cloud/apps/message_service/urls.py
sparrow_cloud/apps/message_service/views.py
sparrow_cloud/apps/message_service/aliyun_amqp/AliyunCredentialsProvider2.py
sparrow_cloud/apps/message_service/aliyun_amqp/AliyunCredentialsProvider3.py
sparrow_cloud/apps/message_service/aliyun_amqp/__init__.py
sparrow_cloud/apps/message_service/aliyun_amqp/connection.py
sparrow_cloud/apps/message_service/aliyun_amqp/receiver.py
sparrow_cloud/apps/message_service/management/__init__.py
sparrow_cloud/apps/message_service/management/commands/__init__.py
sparrow_cloud/apps/message_service/management/commands/_controller.py
sparrow_cloud/apps/message_service/management/commands/_sparrow_rabbitmq_consumer.py
sparrow_cloud/apps/message_service/management/commands/rabbitmq_consumer.py
sparrow_cloud/apps/message_service/migrations/__init__.py
sparrowcloud-5.0.1.dist-info/LICENSE
sparrowcloud-5.0.1.dist-info/METADATA
sparrowcloud-5.0.1.dist-info/WHEEL
sparrowcloud-5.0.1.dist-info/top_level.txt
sparrowcloud-5.0.1.dist-info/RECORD
