Metadata-Version: 2.1
Name: sparrowcloud
Version: 5.0.1
Summary: 基础Django和drf的微服务框架扩展
Home-page: https://gitee.com/sparrow614/sparrow_cloud
Author: sparrow
Author-email: 
License: MIT
Classifier: Development Status :: 4 - Beta
Classifier: Environment :: Web Environment
Classifier: Framework :: Django :: 4.2
Classifier: Programming Language :: Python :: 3.11
Classifier: Topic :: Internet :: WWW/HTTP
Requires-Python: >=3.11
License-File: LICENSE
Requires-Dist: requests>=2.32.3
Requires-Dist: coreapi>=2.3.3
Requires-Dist: PyJWT>=2.9.0
Requires-Dist: openapi-codec>=1.3.2
Requires-Dist: dulwich>=0.22.1
Requires-Dist: pika>=1.3.2
Requires-Dist: cryptography>=43.0.0
Requires-Dist: opentracing>=2.4.0
Requires-Dist: jaeger-client>=4.8.0
Requires-Dist: six>=1.16.0
